{
 "cells": [
  {
   "cell_type": "markdown",
   "source": [
    "# Creating"
   ],
   "metadata": {
    "collapsed": false,
    "pycharm": {
     "name": "#%% md\n"
    }
   }
  },
  {
   "cell_type": "code",
   "execution_count": 1,
   "metadata": {
    "collapsed": true,
    "pycharm": {
     "name": "#%%\n"
    }
   },
   "outputs": [],
   "source": [
    "from dis import dis"
   ]
  },
  {
   "cell_type": "code",
   "execution_count": null,
   "outputs": [],
   "source": [
    "t = (1, 2, 3)\n",
    "l = [1, 2, 3]"
   ],
   "metadata": {
    "collapsed": false,
    "pycharm": {
     "name": "#%%\n"
    }
   }
  },
  {
   "cell_type": "code",
   "execution_count": 4,
   "outputs": [
    {
     "name": "stdout",
     "output_type": "stream",
     "text": [
      "  0           0 RESUME                   0\n",
      "\n",
      "  1           2 LOAD_CONST               0 ((1, 2, 3))\n",
      "              4 RETURN_VALUE\n"
     ]
    }
   ],
   "source": [
    "dis(compile(\"(1,2,3)\", filename=\"string\", mode=\"eval\"))\n",
    "#? creating the whole container as the constant"
   ],
   "metadata": {
    "collapsed": false,
    "pycharm": {
     "name": "#%%\n"
    }
   }
  },
  {
   "cell_type": "code",
   "execution_count": 5,
   "outputs": [
    {
     "name": "stdout",
     "output_type": "stream",
     "text": [
      "  0           0 RESUME                   0\n",
      "\n",
      "  1           2 BUILD_LIST               0\n",
      "              4 LOAD_CONST               0 ((1, 2, 3))\n",
      "              6 LIST_EXTEND              1\n",
      "              8 RETURN_VALUE\n"
     ]
    }
   ],
   "source": [
    "dis(compile(\"[1,2,3]\", filename=\"string\", mode=\"eval\"))\n",
    "#? treating th each element as the constant"
   ],
   "metadata": {
    "collapsed": false,
    "pycharm": {
     "name": "#%%\n"
    }
   }
  },
  {
   "cell_type": "code",
   "execution_count": 9,
   "outputs": [
    {
     "name": "stdout",
     "output_type": "stream",
     "text": [
      "  0           0 RESUME                   0\n",
      "\n",
      "  1           2 LOAD_CONST               0 (1)\n",
      "              4 LOAD_CONST               1 (2)\n",
      "              6 LOAD_CONST               2 (3)\n",
      "              8 LOAD_CONST               0 (1)\n",
      "             10 LOAD_CONST               1 (2)\n",
      "             12 BUILD_LIST               2\n",
      "             14 BUILD_TUPLE              4\n",
      "             16 RETURN_VALUE\n"
     ]
    }
   ],
   "source": [
    "dis(compile(\"(1,2,3,[1,2])\", filename=\"string\", mode=\"eval\"))\n",
    "#? if container contain any mutable object then each element is considered as the constant separately"
   ],
   "metadata": {
    "collapsed": false,
    "pycharm": {
     "name": "#%%\n"
    }
   }
  },
  {
   "cell_type": "code",
   "execution_count": 10,
   "outputs": [
    {
     "name": "stdout",
     "output_type": "stream",
     "text": [
      "  0           0 RESUME                   0\n",
      "\n",
      "  1           2 LOAD_CONST               0 (1)\n",
      "              4 LOAD_CONST               1 (2)\n",
      "              6 LOAD_CONST               2 (3)\n",
      "              8 LOAD_CONST               0 (1)\n",
      "             10 LOAD_CONST               1 (2)\n",
      "             12 BUILD_LIST               2\n",
      "             14 BUILD_LIST               4\n",
      "             16 RETURN_VALUE\n"
     ]
    }
   ],
   "source": [
    "dis(compile(\"[1,2,3,[1,2]]\", filename=\"string\", mode=\"eval\"))\n",
    "#? only difference is it finally need to build the list , there it build the tuple"
   ],
   "metadata": {
    "collapsed": false,
    "pycharm": {
     "name": "#%%\n"
    }
   }
  },
  {
   "cell_type": "code",
   "execution_count": 11,
   "outputs": [],
   "source": [
    "def fn():\n",
    "    pass"
   ],
   "metadata": {
    "collapsed": false,
    "pycharm": {
     "name": "#%%\n"
    }
   }
  },
  {
   "cell_type": "code",
   "execution_count": 12,
   "outputs": [
    {
     "name": "stdout",
     "output_type": "stream",
     "text": [
      "  0           0 RESUME                   0\n",
      "\n",
      "  1           2 LOAD_CONST               0 (1)\n",
      "              4 LOAD_CONST               1 (2)\n",
      "              6 LOAD_CONST               2 (3)\n",
      "              8 LOAD_NAME                0 (fn)\n",
      "             10 BUILD_TUPLE              4\n",
      "             12 RETURN_VALUE\n"
     ]
    }
   ],
   "source": [
    "dis(compile(\"(1,2,3,fn)\", filename=\"string\", mode=\"eval\"))"
   ],
   "metadata": {
    "collapsed": false,
    "pycharm": {
     "name": "#%%\n"
    }
   }
  },
  {
   "cell_type": "code",
   "execution_count": 13,
   "outputs": [
    {
     "name": "stdout",
     "output_type": "stream",
     "text": [
      "  0           0 RESUME                   0\n",
      "\n",
      "  1           2 LOAD_CONST               0 (1)\n",
      "              4 LOAD_CONST               1 (2)\n",
      "              6 LOAD_CONST               2 (3)\n",
      "              8 LOAD_NAME                0 (fn)\n",
      "             10 BUILD_LIST               4\n",
      "             12 RETURN_VALUE\n"
     ]
    }
   ],
   "source": [
    "dis(compile(\"[1,2,3,fn]\", filename=\"string\", mode=\"eval\"))"
   ],
   "metadata": {
    "collapsed": false,
    "pycharm": {
     "name": "#%%\n"
    }
   }
  },
  {
   "cell_type": "code",
   "execution_count": 6,
   "outputs": [],
   "source": [
    "from timeit import timeit"
   ],
   "metadata": {
    "collapsed": false,
    "pycharm": {
     "name": "#%%\n"
    }
   }
  },
  {
   "cell_type": "code",
   "execution_count": 7,
   "outputs": [
    {
     "data": {
      "text/plain": "0.20298349999939092"
     },
     "execution_count": 7,
     "metadata": {},
     "output_type": "execute_result"
    }
   ],
   "source": [
    "timeit(\"(1,2,3,4,5,6,7,8,9)\",number=10_000_000)"
   ],
   "metadata": {
    "collapsed": false,
    "pycharm": {
     "name": "#%%\n"
    }
   }
  },
  {
   "cell_type": "code",
   "execution_count": 8,
   "outputs": [
    {
     "data": {
      "text/plain": "1.4600570000038715"
     },
     "execution_count": 8,
     "metadata": {},
     "output_type": "execute_result"
    }
   ],
   "source": [
    "timeit(\"[1,2,3,4,5,6,7,8,9]\",number=10_000_000)"
   ],
   "metadata": {
    "collapsed": false,
    "pycharm": {
     "name": "#%%\n"
    }
   }
  },
  {
   "cell_type": "markdown",
   "source": [
    "# Coping"
   ],
   "metadata": {
    "collapsed": false,
    "pycharm": {
     "name": "#%% md\n"
    }
   }
  },
  {
   "cell_type": "code",
   "execution_count": 14,
   "outputs": [
    {
     "data": {
      "text/plain": "(2173883554048, 2173883601152)"
     },
     "execution_count": 14,
     "metadata": {},
     "output_type": "execute_result"
    }
   ],
   "source": [
    "t1 = (1,2,3)\n",
    "l1 = [1,2,3]\n",
    "id(t1),id(l1)"
   ],
   "metadata": {
    "collapsed": false,
    "pycharm": {
     "name": "#%%\n"
    }
   }
  },
  {
   "cell_type": "code",
   "execution_count": 15,
   "outputs": [
    {
     "data": {
      "text/plain": "(2173883554048, 2173883554048)"
     },
     "execution_count": 15,
     "metadata": {},
     "output_type": "execute_result"
    }
   ],
   "source": [
    "t2 = tuple(t1)\n",
    "id(t1),id(t2)\n",
    "#? both will same address since the tuple is immutable sequence type"
   ],
   "metadata": {
    "collapsed": false,
    "pycharm": {
     "name": "#%%\n"
    }
   }
  },
  {
   "cell_type": "code",
   "execution_count": 16,
   "outputs": [
    {
     "data": {
      "text/plain": "(2173883601152, 2173883401408)"
     },
     "execution_count": 16,
     "metadata": {},
     "output_type": "execute_result"
    }
   ],
   "source": [
    "l2 = list(l1)\n",
    "id(l1),id(l2)\n",
    "#? will be different since list is mutable"
   ],
   "metadata": {
    "collapsed": false,
    "pycharm": {
     "name": "#%%\n"
    }
   }
  },
  {
   "cell_type": "code",
   "execution_count": 19,
   "outputs": [
    {
     "data": {
      "text/plain": "0.8485425999970175"
     },
     "execution_count": 19,
     "metadata": {},
     "output_type": "execute_result"
    }
   ],
   "source": [
    "timeit('tuple((1,2,3,4,5,6,7,8,9))', number=10_000_000)"
   ],
   "metadata": {
    "collapsed": false,
    "pycharm": {
     "name": "#%%\n"
    }
   }
  },
  {
   "cell_type": "code",
   "execution_count": 18,
   "outputs": [
    {
     "data": {
      "text/plain": "2.9599383999884594"
     },
     "execution_count": 18,
     "metadata": {},
     "output_type": "execute_result"
    }
   ],
   "source": [
    "timeit('list([1,2,3,4,5,6,7,8,9])', number=10_000_000)"
   ],
   "metadata": {
    "collapsed": false,
    "pycharm": {
     "name": "#%%\n"
    }
   }
  },
  {
   "cell_type": "code",
   "execution_count": null,
   "outputs": [],
   "source": [],
   "metadata": {
    "collapsed": false,
    "pycharm": {
     "name": "#%%\n"
    }
   }
  }
 ],
 "metadata": {
  "kernelspec": {
   "display_name": "Python 3",
   "language": "python",
   "name": "python3"
  },
  "language_info": {
   "codemirror_mode": {
    "name": "ipython",
    "version": 2
   },
   "file_extension": ".py",
   "mimetype": "text/x-python",
   "name": "python",
   "nbconvert_exporter": "python",
   "pygments_lexer": "ipython2",
   "version": "2.7.6"
  }
 },
 "nbformat": 4,
 "nbformat_minor": 0
}